Snapshot/__init__.py
Snapshot/snapshot.py
snapshotkockpit-0.0.1.dist-info/LICENSE
snapshotkockpit-0.0.1.dist-info/METADATA
snapshotkockpit-0.0.1.dist-info/WHEEL
snapshotkockpit-0.0.1.dist-info/top_level.txt
snapshotkockpit-0.0.1.dist-info/RECORD
