Metadata-Version: 2.1
Name: snapshotkockpit
Version: 0.0.1
Summary: A library for creating snapshots of data over specified date ranges using Spark.
Author: Naveen Gulati, Shubham Rawat
Author-email: gulati1432@gmail.com, rawatshubham71@gmail.com
Keywords: Snapshot,pyspark,Naveen Gulati,Shubham Rawat
Classifier: Development Status :: 1 - Planning
Classifier: Intended Audience :: Developers
Classifier: Programming Language :: Python :: 3
Classifier: Operating System :: Unix
Classifier: Operating System :: MacOS :: MacOS X
Classifier: Operating System :: Microsoft :: Windows
License-File: LICENSE
